{
  "Aaron Gustafson": {
    "twitter": "AaronGustafson",
    "mastodon": "@Aaron@front-end.social",
    "site": "https://www.aaron-gustafson.com/"
  },
  "Ad Hoc": {
    "twitter": "adhocteam",
    "site": "https://adhoc.team/"
  },
  "Adam Silver": {
    "twitter": "adambsilver",
    "site": "https://adamsilver.io/"
  },
  "Adam Wiggins": {
    "site": "http://about.adamwiggins.com/"
  },
  "Adobe PhoneGap": {
    "twitter": "phonegap",
    "site": "https://blog.phonegap.com/"
  },
  "Adrian Roselli": {
    "twitter": "aardrian",
    "mastodon": "@aardrian@toot.cafe",
    "site": "https://adrianroselli.com/"
  },
  "Adrian Todorov": {
    "site": "https://atodorov.me/"
  },
  "Adrian Zumbrunnen": {
    "twitter": "azumbrunnen_"
  },
  "Ahmad Shadeed": {
    "twitter": "shadeed9",
    "mastodon": "@shadeed9@front-end.social",
    "site": "https://ishadeed.com/"
  },
  "Alan Norbauer": {
    "mastodon": "@alannorbauer@indieweb.social",
    "site": "https://alan.norbauer.com/"
  },
  "Alex Molas": {
    "site": "https://www.alexmolas.com/"
  },
  "Alex Russell": {
    "mastodon": "@slightlyoff@toot.cafe",
    "site": "https://infrequently.org/"
  },
  "Alice Thudt": {
    "site": "https://www.alicethudt.de/"
  },
  "Alistair Shepherd": {
    "mastodon": "@accudio@mastodon.scot",
    "twitter": "accudio",
    "site": "https://alistairshepherd.uk/"
  },
  "Amelia Wattenberger": {
    "twitter": "wattenberger",
    "site": "https://wattenberger.com/"
  },
  "Amy Hupe": {
    "twitter": "amy_hupe",
    "mastodon": "@Amy_Hupe@social.design.systems",
    "site": "https://amyhupe.co.uk/"
  },
  "Ana Rodrigues": {
    "twitter": "ohhelloana",
    "site": "https://ohhelloana.blog/"
  },
  "Andrey Sitnik": {
    "mastodon": "@sitnik_en@mastodon.social",
    "site": "https://sitnik.ru/en/"
  },
  "Andy Bell": {
    "twitter": "hankchizljaw",
    "mastodon": "@belldotbz@mastodon.social",
    "site": "https://hankchizljaw.com/"
  },
  "Anthony Ricaud": {
    "twitter": "anthony_ricaud",
    "site": "https://ricaud.me/"
  },
  "Aral Balkan": {
    "mastodon": "@aral@mastodon.ar.al",
    "site": "https://ar.al/"
  },
  "Ashley Spencer": {
    "twitter": "ashleyyspencer",
    "site": "https://ashleymspencer.com/"
  },
  "Barry Pollard": {
    "twitter": "tunetheweb",
    "mastodon": "@tunetheweb@webperf.social",
    "site": "https://www.tunetheweb.com/"
  },
  "Baymard Institute": {
    "twitter": "Baymard",
    "site": "https://baymard.com/"
  },
  "Ben Francis": {
    "twitter": "bfrancis"
  },
  "Ben Myers": {
    "mastodon": "@ben@a11y.info",
    "site": "https://benmyers.dev/"
  },
  "Bobae Kang": {
    "site": "https://bobaekang.com/"
  },
  "Boris Schapira": {
    "twitter": "borisschapira",
    "site": "https://boris.schapira.dev/"
  },
  "Brad Frost": {
    "twitter": "brad_frost",
    "mastodon": "@brad_frost@mastodon.social",
    "site": "http://bradfrost.com/"
  },
  "Bramus Van Damme": {
    "twitter": "bramus",
    "mastodon": "@bramus@front-end.social",
    "site": "https://www.bram.us/"
  },
  "Brendan Kenny": {
    "twitter": "brendankenny"
  },
  "Brian Louis Ramirez": {
    "twitter": "screenspan",
    "site": "https://screenspan.net/"
  },
  "Bruce Lawson": {
    "twitter": "brucel"
  },
  "Bryan L. Robinson": {
    "twitter": "brob",
    "site": "https://bryanlrobinson.com/"
  },
  "Cariad Eccleston": {
    "mastodon": "@cariad@hachyderm.io",
    "site": "https://www.beep.blog/"
  },
  "Carolina Gilabert": {
    "twitter": "CarolSaysThings",
    "site": "https://carol.gg/"
  },
  "Cassie Evans": {
    "twitter": "cassiecodes",
    "site": "https://www.cassie.codes/"
  },
  "Cee-Roo": {
    "site": "http://www.ceeroo.ch/"
  },
  "Charity Majors": {
    "twitter": "mipsytipsy",
    "site": "https://charity.wtf/"
  },
  "Charlie Owen": {
    "twitter": "sonniesedge",
    "site": "https://sonniesedge.co.uk/"
  },
  "Chen Hui Jing": {
    "twitter": "hj_chen",
    "site": "https://www.chenhuijing.com/"
  },
  "Chris Coyier": {
    "twitter": "chriscoyier",
    "mastodon": "@chriscoyier@front-end.social",
    "site": "https://chriscoyier.net/"
  },
  "Chris Ferdinandi": {
    "twitter": "ChrisFerdinandi",
    "mastodon": "@cferdinandi@mastodon.social",
    "site": "https://gomakethings.com/"
  },
  "Chris James": {
    "mastodon": "@quii@mastodon.cloud",
    "site": "https://quii.dev/"
  },
  "Chris Nielsen": {
    "twitter": "chrisnielsen123"
  },
  "Chris Taylor": {
    "twitter": "mrwiblog",
    "site": "https://www.stillbreathing.co.uk/"
  },
  "Chris Zacharias": {
    "twitter": "zacman85",
    "site": "https://www.chriszacharias.com/"
  },
  "Christian Heilmann": {
    "twitter": "codepo8",
    "mastodon": "@codepo8@toot.cafe ",
    "site": "https://christianheilmann.com/"
  },
  "Christian Holst": {
    "twitter": "kiehnholst"
  },
  "Christine Vallaure": {
    "twitter": "moonlearning",
    "site": "https://www.moonlearning.io/"
  },
  "Cliff Crocker": {
    "mastodon": "@cliff@webperf.social"
  },
  "CloudCannon": {
    "mastodon": "@cloudcannon@techhub.social",
    "site": "https://cloudcannon.com/"
  },
  "Cody Lindley": {
    "twitter": "codylindley"
  },
  "Coralie Mercier": {
    "mastodon": "@koalie@mastodon.social"
  },
  "Daniel Miessler": {
    "twitter": "danielmiessler",
    "site": "https://danielmiessler.com/"
  },
  "Darek Kay": {
    "site": "https://darekkay.com/",
    "mastodon": "@darekkay@fosstodon.org"
  },
  "Dave Ceddia": {
    "twitter": "dceddia"
  },
  "Dave Rupert": {
    "site": "https://daverupert.com/",
    "mastodon": "@davatron5000@mastodon.social"
  },
  "Dave Winer": {
    "site": "http://davewiner.com/",
    "mastodon": "@davew@mastodon.social"
  },
  "David Heinemeier Hansson": {
    "twitter": "dhh"
  },
  "David Large": {
    "mastodon": "@avidlarge@fosstodon.org"
  },
  "David Pierce": {
    "mastodon": "@davidpierce@mastodon.social"
  },
  "David Ross": {
    "mastodon": "@DRoss@hachyderm.io"
  },
  "Dion Almaer": {
    "site": "https://blog.almaer.com/",
    "mastodon": "@dalmaer@indieweb.social"
  },
  "Dominikus Baur": {
    "site": "https://do.minik.us/",
    "mastodon": "@dominikus@vis.social"
  },
  "Donnie D'Amato": {
    "twitter": "donniedamato",
    "mastodon": "@donniedamato@mastodon.social",
    "site": "https://donnie.damato.design/"
  },
  "Elaina Natario": {
    "mastodon": "@elaina@mastodon.lol",
    "site": "https://www.elainanatario.com/"
  },
  "Elie Sloïm": {
    "twitter": "ElieSl",
    "site": "https://www.opquast.com/"
  },
  "Elizabeth Tai": {
    "site": "https://elizabethtai.com/",
    "mastodon": "@liztai@hachyderm.io"
  },
  "Emerson Loustau": {
    "twitter": "emersonthis",
    "site": "https://emersonthis.com/"
  },
  "Eric Bailey": {
    "twitter": "ericwbailey",
    "mastodon": "@eric@social.ericwbailey.website",
    "site": "https://ericwbailey.design/"
  },
  "Eric Portis": {
    "site": "https://ericportis.com/",
    "mastodon": "@eeeps@front-end.social",
    "twitter": "etportis"
  },
  "Ethan Marcotte": {
    "twitter": "beep",
    "site": "https://ethanmarcotte.com/"
  },
  "Evan Minto": {
    "twitter": "VamptVo",
    "site": "https://evanminto.com/"
  },
  "Ewen Bell": {
    "mastodon": "@ewen@photog.social",
    "site": "https://ewenbell.com/"
  },
  "Farhad Manjoo": {
    "twitter": "fmanjoo"
  },
  "Florens Verschelde": {
    "twitter": "fvsch",
    "site": "https://fvsch.com/"
  },
  "François Nonnenmacher": {
    "mastodon": "@pdwn@mamot.fr",
    "site": "https://www.padawan.info/"
  },
  "Gábor Ugray": {
    "site": "https://jealousmarkup.xyz/",
    "mastodon": "@twilliability@genart.social"
  },
  "Glenn Fleishman": {
    "mastodon": "@glennf@twit.social",
    "site": "https://glog.glennf.com/"
  },
  "Grant for the Web": {
    "twitter": "GrantForTheWeb",
    "site": "https://www.grantfortheweb.org/"
  },
  "HTTP Archive": {
    "twitter": "HTTPArchive",
    "site": "https://httparchive.org/"
  },
  "Harry Roberts": {
    "mastodon": "@csswizardry@webperf.social",
    "twitter": "csswizardry",
    "site": "https://csswizardry.com/"
  },
  "Heather Buchel": {
    "mastodon": "@hbuchel@hachyderm.io",
    "site": "https://heather-buchel.com/"
  },
  "Henk van Houtum": {
    "twitter": "henkvanhoutum",
    "site": "https://henkvanhoutum.nl/"
  },
  "Henny Swan": {
    "twitter": "iheni"
  },
  "Henry Desroches": {
    "twitter": "xdesro",
    "site": "https://henry.codes/"
  },
  "Heydon Pickering": {
    "twitter": "heydonworks",
    "mastodon": "@heydon@mastodon.social",
    "site": "https://heydonworks.com/"
  },
  "Hidde de Vries": {
    "twitter": "hdv"
  },
  "Hubert Sablonnière": {
    "twitter": "hsablonniere",
    "site": "https://www.hsablonniere.com/"
  },
  "Hynek Schlawack": {
    "twitter": "hynek",
    "site": "https://hynek.me/"
  },
  "Jack Schofield": {
    "twitter": "jackschofield"
  },
  "Jake Archibald": {
    "mastodon": "@jaffathecake@mastodon.social",
    "twitter": "jaffathecake",
    "site": "https://jakearchibald.com/"
  },
  "Jake Lazaroff": {
    "site": "https://jakelazaroff.com/",
    "mastodon": "@jakelazaroff@mastodon.social"
  },
  "Jakob Nielsen": {
    "twitter": "nngroup",
    "site": "https://www.nngroup.com/"
  },
  "Jared White": {
    "site": "https://jaredwhite.com/",
    "mastodon": "@jaredwhite@indieweb.social"
  },
  "Jason Grigsby": {
    "twitter": "grigs",
    "mastodon": "@grigs@front-end.social",
    "site": "http://www.userfirstweb.com/"
  },
  "Jason Pamental": {
    "twitter": "jpamental"
  },
  "Jason Santa Maria": {
    "mastodon": "@jasonsantamaria@typo.social",
    "site": "https://jasonsantamaria.com/"
  },
  "Jay Freestone": {
    "twitter": "jayfreestone"
  },
  "Jeff Delaney": {
    "twitter": "Jeffdelaney23",
    "site": "https://jeffdelaney.me/"
  },
  "Jeff Posnick": {
    "mastodon": "@jeffposnick@hachyderm.io",
    "site": "https://jeffy.info/"
  },
  "Jen Simmons": {
    "twitter": "jensimmons",
    "site": "https://jensimmons.com/"
  },
  "Jenni Nadler": {
    "site": "https://www.jenninadler.com/"
  },
  "Jens Oliver Meiert": {
    "twitter": "j9t",
    "site": "https://meiert.com/"
  },
  "Jeremy Keith": {
    "twitter": "adactio",
    "mastodon": "@adactio@mastodon.social",
    "site": "https://adactio.com/"
  },
  "Jeremy Wagner": {
    "twitter": "malchata",
    "site": "https://jeremy.codes/"
  },
  "Jessica Davies": {
    "twitter": "jessdaviesmk"
  },
  "Jim Nielsen": {
    "twitter": "jimniels",
    "site": "https://blog.jim-nielsen.com/"
  },
  "Joachim Robert": {
    "site": "https://blog.professeurjoachim.com/",
    "mastodon": "@joachim@boitam.eu"
  },
  "Joe Liccini": {
    "site": "https://www.webperf.tips/"
  },
  "Joel Spolsky": {
    "twitter": "spolsky",
    "site": "https://www.joelonsoftware.com/"
  },
  "Johan Halse": {
    "twitter": "hejsna",
    "site": "https://johan.hal.se/"
  },
  "Johannes Odland": {
    "mastodon": "@johannes@front-end.social",
    "site": "https://johannesodland.github.io/"
  },
  "Jon Sneyers": {
    "twitter": "jonsneyers",
    "site": "https://sneyers.info/"
  },
  "Jonathan Griffin": {
    "twitter": "thewebmastercom",
    "site": "https://www.thewebmaster.com/"
  },
  "Josh Collinsworth": {
    "twitter": "jjcollinsworth",
    "mastodon": "@collinsworth@mastodon.sandwich.net",
    "site": "https://joshcollinsworth.com/"
  },
  "Josh W. Comeau": {
    "mastodon": "@joshwcomeau@bird.makeup",
    "twitter": "joshwcomeau",
    "site": "https://www.joshwcomeau.com/"
  },
  "Jérôme Coupé": {
    "twitter": "jeromecoupe",
    "site": "https://www.webstoemp.com/"
  },
  "Karl Dubost": {
    "site": "https://www.otsukare.info/"
  },
  "Karl Groves": {
    "mastodon": "@karlgroves@mastodon.social",
    "site": "https://karlgroves.com/"
  },
  "Karolina Szczur": {
    "mastodon": "@fox@front-end.social",
    "twitter": "fox",
    "site": "https://thefox.is/"
  },
  "Katharine Schwab": {
    "twitter": "kschwabable"
  },
  "Kathleen McMahon": {
    "mastodon": "@resource11@front-end.social",
    "site": "https://www.kathleenmcmahon.dev/"
  },
  "Keir Watson": {
    "site": "https://herbidacious.calamus.graphics/"
  },
  "Kev Bonett": {
    "twitter": "basherkev"
  },
  "Kev Quirk": {
    "twitter": "kevquirk",
    "mastodon": "@kev@fosstodon.org",
    "site": "https://kevquirk.com/"
  },
  "Kevin Farrugia": {
    "mastodon": "@kevinfarrugia@webperf.social",
    "site": "https://imkev.dev/"
  },
  "Kilian Valkhof": {
    "site": "https://kilianvalkhof.com/",
    "mastodon": "@Kilian@mastodon.social"
  },
  "Kitty Giraudel": {
    "twitter": "KittyGiraudel",
    "site": "https://kittygiraudel.com/"
  },
  "Kornel": {
    "twitter": "kornelski",
    "site": "https://kornel.ski/"
  },
  "Kévin Dunglas": {
    "twitter": "dunglas"
  },
  "Laura Kalbag": {
    "twitter": "laurakalbag",
    "site": "https://laurakalbag.com/"
  },
  "Laurel Schwulst": {
    "site": "https://laurelschwulst.com/"
  },
  "Leanne Renard": {
    "site": "https://leannerenard.co.uk/",
    "mastodon": "@leannecodes@mastodon.social"
  },
  "Lee Reilly": {
    "twitter": "leereilly",
    "site": "https://leereilly.net/"
  },
  "Leon de Korte": {
    "twitter": "dekorteleon",
    "site": "https://www.leondekorte.nl/"
  },
  "Léonie Watson": {
    "twitter": "LeonieWatson",
    "site": "https://tink.uk/"
  },
  "Liridon Hasani": {
    "site": "https://liridon.dev/"
  },
  "Lisa Charlotte Rost": {
    "twitter": "lisacrost",
    "site": "https://lisacharlotterost.de/"
  },
  "Luke Wroblewski": {
    "site": "https://www.lukew.com/"
  },
  "Lydia Hallie": {
    "site": "https://www.lydiahallie.com/"
  },
  "Maarten Van Hoof": {
    "twitter": "mrtnvh",
    "site": "https://mrtnvh.com/"
  },
  "Maite Vermeulen": {
    "twitter": "maitevermeulen"
  },
  "MajorLinux": {
    "site": "https://majorlinux.com/"
  },
  "Malte Ubl": {
    "twitter": "cramforce",
    "site": "https://www.industrialempathy.com/"
  },
  "Manuel Matuzović": {
    "twitter": "mmatuzo",
    "mastodon": "@matuzo@mastodon.social",
    "site": "https://www.matuzo.at/"
  },
  "Marc": {
    "site": "https://atthis.link/"
  },
  "Marco Bellinaso": {
    "twitter": "mbellinaso"
  },
  "Marco Hengstenberg": {
    "twitter": "nice2meatu",
    "mastodon": "@nice2meatu@mastodon.social"
  },
  "Marcus Herrmann": {
    "mastodon": "@marcus@mastodon.social",
    "site": "https://marcus.io/"
  },
  "Marcy Sutton": {
    "twitter": "marcysutton",
    "site": "https://marcysutton.com/"
  },
  "Maria Farrell": {
    "twitter": "mariafarrell"
  },
  "Marie Manandise": {
    "site": "https://marie-manandise.net/"
  },
  "Mark Llobrera": {
    "mastodon": "@markllobrera@mastodon.social",
    "twitter": "dirtystylus",
    "site": "https://www.markllobrera.com/"
  },
  "Mark McGranaghan": {
    "site": "https://markmcgranaghan.com/"
  },
  "Mark Nottingham": {
    "twitter": "mnot",
    "site": "https://www.mnot.net/"
  },
  "Martin Kleppmann": {
    "site": "https://martin.kleppmann.com/"
  },
  "Matt Anderson": {
    "twitter": "mattanddesign",
    "site": "https://mattanddesign.com/"
  },
  "Matt Burgess": {
    "twitter": "mattburgess1",
    "site": "http://mattburgess.co/"
  },
  "Matt Cambion": {
    "site": "https://starbreaker.org/"
  },
  "Matt Hobbs": {
    "twitter": "TheRealNooshu",
    "site": "https://nooshu.github.io/"
  },
  "Matthias Ott": {
    "twitter": "m_ott",
    "mastodon": "@matthiasott@mastodon.social",
    "site": "https://matthiasott.com/"
  },
  "Max Böck": {
    "twitter": "mxbck",
    "mastodon": "@mxbck@indieweb.social",
    "site": "https://mxb.dev/"
  },
  "Maximiliano Firtman": {
    "twitter": "firt",
    "site": "https://firt.dev/"
  },
  "Michael Rose": {
    "twitter": "mmistakes",
    "site": "https://mademistakes.com/"
  },
  "Michael Scharnagl": {
    "twitter": "justmarkup",
    "site": "https://justmarkup.com/"
  },
  "Michael Wolfe": {
    "twitter": "michaelrwolfe"
  },
  "Michelle Barker": {
    "mastodon": "@michelle@front-end.social",
    "twitter": "MicheBarks",
    "site": "https://www.michellebarker.co.uk/"
  },
  "Mike Riethmuller": {
    "twitter": "MikeRiethmuller",
    "site": "https://www.madebymike.com.au/"
  },
  "Miriam Suzanne": {
    "twitter": "mirisuzanne",
    "site": "https://www.miriamsuzanne.com/"
  },
  "Miško Hevery": {
    "twitter": "mhevery",
    "site": "http://misko.hevery.com/"
  },
  "Monica Dinculescu": {
    "twitter": "notwaldorf"
  },
  "Mozilla": {
    "mastodon": "@mozilla@mozilla.social",
    "site": "https://www.mozilla.org/"
  },
  "Natalie Weizenbaum": {
    "twitter": "nex3",
    "mastodon": "@nex3@mastodon.social"
  },
  "Nate Baldwin": {
    "twitter": "NateBaldwinArt",
    "site": "https://natebaldw.in/"
  },
  "Nelson Minar": {
    "mastodon": "@nelson@lgbt.io",
    "site": "https://www.somebits.com/"
  },
  "Nic Chan": {
    "mastodon": "@NicMakesStuff@indieweb.social",
    "site": "https://www.nicchan.me/"
  },
  "Nick Routley": {
    "twitter": "nickroutley"
  },
  "Nick Winkler": {
    "site": "https://www.thewinklergroup.net/"
  },
  "Nicolas Goutay": {
    "twitter": "Phacks",
    "site": "https://phacks.dev/"
  },
  "Nikita Prokopov": {
    "site": "https://tonsky.me/"
  },
  "Nilay Patel": {
    "mastodon": "@nilaypatel@mastodon.social"
  },
  "Nils Binder": {
    "twitter": "supremebeing09",
    "site": "https://ichimnetz.com/"
  },
  "Nolan Lawson": {
    "mastodon": "@nolan@toot.cafe",
    "site": "https://nolanlawson.com/"
  },
  "Opquast": {
    "twitter": "opquast",
    "site": "https://www.opquast.com/"
  },
  "Orange Digital Accessibility": {
    "site": "https://a11y-guidelines.orange.com/"
  },
  "Owen Williams": {
    "twitter": "ow"
  },
  "Patrick Brosset": {
    "mastodon": "@patrickbrosset@mas.to",
    "site": "https://patrickbrosset.com/"
  },
  "Paul Calvano": {
    "mastodon": "@paulcalvano@webperf.social",
    "twitter": "paulcalvano",
    "site": "https://paulcalvano.com/"
  },
  "Paul Hebert": {
    "mastodon": "@paulhebert@sunny.garden",
    "site": "http://paulhebertdesigns.com/"
  },
  "Paul Kinlan": {
    "twitter": "Paul_Kinlan"
  },
  "Paula": {
    "mastodon": "@PaulaToThePeople@climatejustice.social",
    "site": "https://write.wien.rocks/paula/"
  },
  "Peter van Hardenberg": {
    "twitter": "pvh"
  },
  "Philip Walton": {
    "twitter": "philwalton",
    "site": "https://philipwalton.com/"
  },
  "Poul-Henning Kamp": {
    "twitter": "bsdphk"
  },
  "Rachel Andrew": {
    "twitter": "rachelandrew",
    "site": "https://rachelandrew.co.uk/"
  },
  "Ramesh Periyathambi": {
    "twitter": "ebaytech",
    "site": "https://www.ebayinc.com/stories/blogs/tech/"
  },
  "Raymond Camden": {
    "site": "https://www.raymondcamden.com/",
    "mastodon": "@raymondcamden@mastodon.social"
  },
  "Remy Sharp": {
    "twitter": "rem",
    "site": "https://remysharp.com/"
  },
  "Rich Harris": {
    "twitter": "Rich_Harris"
  },
  "Richard Hemmer": {
    "mastodon": "@richard@hemmer.land",
    "site": "https://stormgrass.com/"
  },
  "Richard Ishida": {
    "twitter": "r12a",
    "site": "https://r12a.github.io/"
  },
  "Rob O'Leary": {
    "site": "https://www.roboleary.net/"
  },
  "Rob Dubbin": {
    "mastodon": "@dubbin@friend.camp"
  },
  "Robb Knight": {
    "site": "https://rknight.me/",
    "mastodon": "@robb@social.lol"
  },
  "Rob Weychert": {
    "twitter": "robweychert"
  },
  "Robin Berjon": {
    "site": "https://berjon.com/",
    "mastodon": "@robin@mastodon.social"
  },
  "Robin Rendle": {
    "twitter": "robinrendle",
    "site": "https://www.robinrendle.com/"
  },
  "Roderick Gadellaa": {
    "site": "https://webventures.rejh.nl/",
    "mastodon": "@rgadellaa@mastodon.social"
  },
  "Roman Komarov": {
    "mastodon": "@kizu@front-end.social",
    "site": "https://kizu.dev/"
  },
  "Romaric Pascal": {
    "twitter": "romaricpascal",
    "site": "https://romaricpascal.is/"
  },
  "Ruud van Asseldonk": {
    "site": "https://ruudvanasseldonk.com/",
    "mastodon": "@ruuda@fosstodon.org"
  },
  "Ryan Barrett": {
    "twitter": "schnarfed",
    "mastodon": "@snarfed.org@snarfed.org"
  },
  "Ryan Mulligan": {
    "twitter": "hexagoncircle",
    "site": "https://hexagoncircle.com/"
  },
  "Rémy Parmentier": {
    "twitter": "HTeuMeuLeu",
    "site": "https://www.hteumeuleu.fr/"
  },
  "Sam Morris": {
    "twitter": "sammorrisdesign",
    "site": "https://sammorr.is/"
  },
  "Sara Soueidan": {
    "twitter": "SaraSoueidan",
    "site": "https://www.sarasoueidan.com/"
  },
  "Sarah Dayan": {
    "twitter": "frontstuff_io",
    "site": "https://frontstuff.io/"
  },
  "Scott Jehl": {
    "twitter": "scottjehl",
    "mastodon": "@scottjehl@mstdn.social",
    "site": "https://scottjehl.com/"
  },
  "Sean Hollister": {
    "mastodon": "@seanhollister@mastodon.world"
  },
  "Sebastian Greger": {
    "site": "https://sebastiangreger.net/",
    "mastodon": "@sebastiangreger@sebastiangreger.net"
  },
  "Sebastian Hermida": {
    "twitter": "sbastn"
  },
  "Sebastiano Guerriero": {
    "twitter": "guerriero_se",
    "site": "https://codyhouse.co/"
  },
  "Shaun Bent": {
    "twitter": "shaunbent",
    "site": "https://www.shaunbent.co.uk/"
  },
  "Shawn Cheris": {
    "site": "https://www.behance.net/shawncheris"
  },
  "Sia Karamalegos": {
    "mastodon": "@sia@front-end.social",
    "site": "https://sia.codes/"
  },
  "Simon Hearne": {
    "twitter": "simonhearne",
    "site": "https://simonhearne.com/"
  },
  "Stephanie Eckles": {
    "mastodon": "@5t3ph@front-end.social",
    "site": "https://thinkdobecreate.com/"
  },
  "Stéphanie Walter": {
    "twitter": "walterstephanie",
    "site": "https://stephaniewalter.design/"
  },
  "Steve Messer": {
    "site": "https://visitmy.website/",
    "mastodon": "@stevenjmesser@indieweb.social"
  },
  "Steve Souders": {
    "twitter": "Souders"
  },
  "Stoyan Stefanov": {
    "site": "https://www.phpied.com/"
  },
  "Surma": {
    "twitter": "DasSurma",
    "site": "https://dassur.ma/"
  },
  "Tammy Everts": {
    "twitter": "tameverts",
    "mastodon": "@tammy@webperf.social"
  },
  "Tantek Çelik": {
    "twitter": "t",
    "mastodon": "@tantek.com@tantek.com",
    "site": "https://tantek.com/"
  },
  "Taylor Hunt": {
    "twitter": "tigt_",
    "site": "https://ti.gt/"
  },
  "Terence Eden": {
    "twitter": "edent",
    "mastodon": "@Edent@mastodon.social",
    "site": "https://shkspr.mobi/blog/"
  },
  "Thoughtworks": {
    "twitter": "thoughtworks",
    "site": "https://www.thoughtworks.com/"
  },
  "Tom MacWright": {
    "mastodon": "@tmcw@mastodon.social",
    "site": "https://macwright.com/"
  },
  "Tomas Pueyo": {
    "site": "https://unchartedterritories.tomaspueyo.com/"
  },
  "Tyce Clee": {
    "twitter": "iamtyce",
    "site": "http://www.iamtyce.com/"
  },
  "Tyler Gaw": {
    "mastodon": "@tylergaw@mastodon.social",
    "site": "https://tylergaw.com"
  },
  "Tim Berners-Lee": {
    "twitter": "timberners_lee"
  },
  "Tim Kadlec": {
    "twitter": "tkadlec",
    "site": "http://timkadlec.com/"
  },
  "Tim Vereecke": {
    "twitter": "timvereecke",
    "mastodon": "@TimVereecke@mastodon.social"
  },
  "Tom Greenwood": {
    "twitter": "eatwholegrain",
    "site": "https://www.wholegraindigital.com/"
  },
  "Toni Sagristà": {
    "mastodon": "@jumpinglangur@mastodon.social",
    "site": "https://tonisagrista.com/"
  },
  "Travis Turner": {
    "site": "https://github.com/Travis-Turner"
  },
  "Trey Harris": {
    "twitter": "treyethan"
  },
  "Troy Hunt": {
    "twitter": "troyhunt"
  },
  "Trys Mudford": {
    "twitter": "trysmudford",
    "mastodon": "@trys@mastodon.social",
    "site": "https://www.trysmudford.com/"
  },
  "Tutorspree": {
    "site": "http://www.tutorspree.com/about"
  },
  "Tyler Sticka": {
    "twitter": "tylersticka",
    "mastodon": "@tylersticka@mastodon.social",
    "site": "https://tylersticka.com/"
  },
  "Vadim Makeev": {
    "twitter": "pepelsbey_dev",
    "mastodon": "@pepelsbey@mastodon.social",
    "site": "https://pepelsbey.dev/"
  },
  "Vasilis van Gemert": {
    "mastodon": "@vasilis@social.vasilis.nl",
    "site": "https://vasilis.nl/"
  },
  "Vesa Lehtimäki": {
    "mastodon": "@avanaut@mastodon.art",
    "site": "https://avanaut.com/"
  },
  "Vincent De Oliveira": {
    "twitter": "iamvdo",
    "site": "https://iamvdo.me/"
  },
  "Xiao Zhuo Jia": {
    "twitter": "XiaoZhuoJia",
    "site": "http://www.miragecraft.com/"
  },
  "Yoav Weiss": {
    "twitter": "yoavweiss",
    "site": "https://blog.yoav.ws/"
  },
  "Yuan Chuan": {
    "twitter": "yuanchuan23"
  },
  "Zach Leatherman": {
    "twitter": "zachleat",
    "mastodon": "@zachleat@zachleat.com",
    "site": "https://www.zachleat.com"
  },
  "Ziemek Bućko": {
    "twitter": "ziemek_bucko"
  },
  "m4dz": {
    "twitter": "m4d_z",
    "site": "https://m4dz.net/"
  }
}
